{
  "parent": "minecraft:recipes/root",
  "criteria": {
    "has_polished_almentra": {
      "conditions": {
        "items": [
          {
            "items": [
              "excessive_building:polished_almentra"
            ]
          }
        ]
      },
      "trigger": "minecraft:inventory_changed"
    },
    "has_the_recipe": {
      "conditions": {
        "recipe": "excessive_building:polished_almentra_slab"
      },
      "trigger": "minecraft:recipe_unlocked"
    }
  },
  "requirements": [
    [
      "has_polished_almentra",
      "has_the_recipe"
    ]
  ],
  "rewards": {
    "recipes": [
      "excessive_building:polished_almentra_slab"
    ]
  },
  "sends_telemetry_event": false
}