{
  "parent": "minecraft:recipes/root",
  "criteria": {
    "has_the_recipe": {
      "conditions": {
        "recipe": "minecraft:thick_paper_stairs"
      },
      "trigger": "minecraft:recipe_unlocked"
    },
    "has_thick_paper_block": {
      "conditions": {
        "items": [
          {
            "items": "excessive_building:thick_paper_block"
          }
        ]
      },
      "trigger": "minecraft:inventory_changed"
    }
  },
  "requirements": [
    [
      "has_the_recipe",
      "has_thick_paper_block"
    ]
  ],
  "rewards": {
    "recipes": [
      "minecraft:thick_paper_stairs"
    ]
  }
}